bitstore.py
bitstore-0.0.1.dist-info/LICENCE.txt
bitstore-0.0.1.dist-info/METADATA
bitstore-0.0.1.dist-info/WHEEL
bitstore-0.0.1.dist-info/top_level.txt
bitstore-0.0.1.dist-info/RECORD
