Metadata-Version: 2.1
Name: bitstore
Version: 0.0.1
Summary: This library contains functions to create, interpret and manipulate sequences of bits stored in integers.
Home-page: https://github.com/JesperGlas/jgbitlib
Author: Jesper Glas
Author-email: jesper.glas@gmail.com
License: UNKNOWN
Platform: UNKNOWN
Provides-Extra: dev
Requires-Dist: check-manifest (>=0.45) ; extra == 'dev'
Requires-Dist: pytest (>=6.1.2) ; extra == 'dev'
Requires-Dist: twine (>=3.2.0) ; extra == 'dev'
